README.md
setup.cfg
setup.py
gcredstash/__init__.py
gcredstash/config.py
gcredstash/keystore.py
gcredstash/kms.py
gcredstash/main.py
gcredstash.egg-info/PKG-INFO
gcredstash.egg-info/SOURCES.txt
gcredstash.egg-info/dependency_links.txt
gcredstash.egg-info/entry_points.txt
gcredstash.egg-info/requires.txt
gcredstash.egg-info/top_level.txt