Metadata-Version: 1.1
Name: gcredstash
Version: 1.0.1
Summary: A Credential Management Tool using Google Cloud KMS and Datastore
Home-page: https://github.com/RajeshHegde/gcredstash
Author: Rajesh Hegde
Author-email: UNKNOWN
License: UNKNOWN
Platform: UNKNOWN
Classifier: Intended Audience :: Developers
Classifier: Intended Audience :: System Administrators
